pcser/__init__.py
pcser/load.py
pcser/path.py
pcser/src/Importance.py
pcser/src/Model.py
pcser/src/Plot.py
pcser/src/Preprocessing.py
pcser/src/__init__.py
pcser/util/Reader.py
pcser/util/Writer.py
pcser/util/__init__.py
pcser-0.0.2.dist-info/LICENSE
pcser-0.0.2.dist-info/METADATA
pcser-0.0.2.dist-info/WHEEL
pcser-0.0.2.dist-info/RECORD
