Metadata-Version: 2.1
Name: pcser
Version: 0.0.2
Summary: protein corona stealth effect prediction
License: GPL-3.0
Author: Jianfeng Sun
Author-email: jianfeng.sunmt@gmail.com
Requires-Python: >=3.11,<4.0
Classifier: License :: OSI Approved :: GNU General Public License v3 (GPLv3)
Classifier: Programming Language :: Python :: 3
Classifier: Programming Language :: Python :: 3.11
Classifier: Programming Language :: Python :: 3.12
Requires-Dist: click (>=8.1.7,<9.0.0)
Requires-Dist: llvmlite (==0.40.1)
Requires-Dist: matplotlib (>=3.8.3,<4.0.0)
Requires-Dist: numpy (==1.24.1)
Requires-Dist: pyfiglet (>=1.0.2,<2.0.0)
Requires-Dist: scikit-learn (>=1.4.1.post1,<2.0.0)
Requires-Dist: seaborn (>=0.13.2,<0.14.0)
Requires-Dist: shap (>=0.44.1,<0.45.0)
